pythontemplateit.py
pythontemplateit-0.2.0.dist-info/LICENSE
pythontemplateit-0.2.0.dist-info/METADATA
pythontemplateit-0.2.0.dist-info/WHEEL
pythontemplateit-0.2.0.dist-info/RECORD
