Metadata-Version: 2.3
Name: PythonTemplateIt
Version: 0.2.0
Summary: Template for new Python projects.
License: MIT
Author: Hendrik du Toit
Author-email: hendrik@brightedge.co.za
Maintainer: Hendrik du Toit
Maintainer-email: hendrikdt@citiqprepaid.co.za
Requires-Python: >=3.10
Classifier: Development Status :: 4 - Beta
Classifier: Intended Audience :: Developers
Classifier: Intended Audience :: Information Technology
Classifier: Intended Audience :: System Administrators
Classifier: License :: OSI Approved :: MIT License
Classifier: Topic :: Software Development :: Libraries :: Python Modules
Classifier: Topic :: System :: Archiving :: Packaging
Classifier: Programming Language :: Python :: 3.10
Classifier: Programming Language :: Python :: 3.11
Classifier: Programming Language :: Python :: 3.12
Classifier: Programming Language :: Python :: 3.13
Project-URL: Changelog, https://github.com/BrightEdgeeServices/PythonTemplateIt/blob/enhancement/master/ReleaseNotes.md
Project-URL: Homepage, https://github.com/BrightEdgeeServices/PythonTemplateIt
Project-URL: Repository, https://github.com/BrightEdgeeServices/PythonTemplateIt.git
Project-URL: issues, https://github.com/BrightEdgeeServices/PythonTemplateIt/issues
